{
  "$schema": "https://developer.microsoft.com/json-schemas/fabric/item/report/definition/visualContainer/2.1.0/schema.json",
  "name": "6c9aa32abaab74f8067d",
  "position": {
    "x": 133.05370955441774,
    "y": 128.18248175182484,
    "z": 5000,
    "height": 42.043795620437962,
    "width": 149.78102189781023,
    "tabOrder": 7000
  },
  "visual": {
    "visualType": "slicer",
    "query": {
      "queryState": {
        "Values": {
          "projections": [
            {
              "field": {
                "Column": {
                  "Expression": {
                    "SourceRef": {
                      "Entity": "Parâmetro Cadastros Clientes"
                    }
                  },
                  "Property": "Parâmetro Cadastros CLientes"
                }
              },
              "queryRef": "Parâmetro Cadastros CLientes.Parâmetro Cadastros CLientes",
              "nativeQueryRef": "Parâmetro Cadastros CLientes",
              "active": true
            }
          ]
        }
      }
    },
    "objects": {
      "header": [
        {
          "properties": {
            "show": {
              "expr": {
                "Literal": {
                  "Value": "false"
                }
              }
            }
          }
        }
      ],
      "data": [
        {
          "properties": {
            "mode": {
              "expr": {
                "Literal": {
                  "Value": "'Dropdown'"
                }
              }
            }
          }
        }
      ],
      "selection": [
        {
          "properties": {
            "strictSingleSelect": {
              "expr": {
                "Literal": {
                  "Value": "true"
                }
              }
            }
          }
        }
      ],
      "items": [
        {
          "properties": {
            "textSize": {
              "expr": {
                "Literal": {
                  "Value": "10D"
                }
              }
            },
            "fontFamily": {
              "expr": {
                "Literal": {
                  "Value": "'wf_standard-font, helvetica, arial, sans-serif'"
                }
              }
            },
            "fontColor": {
              "solid": {
                "color": {
                  "expr": {
                    "ThemeDataColor": {
                      "ColorId": 1,
                      "Percent": 0
                    }
                  }
                }
              }
            }
          }
        }
      ],
      "general": [
        {
          "properties": {
            "filter": {
              "filter": {
                "Version": 2,
                "From": [
                  {
                    "Name": "p",
                    "Entity": "Parâmetro Cadastros Clientes",
                    "Type": 0
                  }
                ],
                "Where": [
                  {
                    "Condition": {
                      "In": {
                        "Expressions": [
                          {
                            "Column": {
                              "Expression": {
                                "SourceRef": {
                                  "Source": "p"
                                }
                              },
                              "Property": "Parâmetro Cadastros CLientes Campos"
                            }
                          }
                        ],
                        "Values": [
                          [
                            {
                              "Literal": {
                                "Value": "'''bi_view_comercial''[cliente_codigo_nome]'"
                              }
                            }
                          ]
                        ]
                      }
                    },
                    "Annotations": {
                      "filterExpressionMetadata": {
                        "expressions": [
                          {
                            "Column": {
                              "Expression": {
                                "SourceRef": {
                                  "Entity": "Parâmetro Cadastros Clientes"
                                }
                              },
                              "Property": "Parâmetro Cadastros CLientes"
                            }
                          }
                        ],
                        "decomposedIdentities": {
                          "values": [
                            [
                              {
                                "0": [
                                  {
                                    "Literal": {
                                      "Value": "'''bi_view_comercial''[cliente_codigo_nome]'"
                                    }
                                  }
                                ]
                              }
                            ]
                          ],
                          "columns": [
                            {
                              "value": {
                                "Column": {
                                  "Expression": {
                                    "SourceRef": {
                                      "Entity": "Parâmetro Cadastros Clientes"
                                    }
                                  },
                                  "Property": "Parâmetro Cadastros CLientes Campos"
                                }
                              }
                            }
                          ]
                        },
                        "valueMap": [
                          {
                            "0": "Cliente"
                          }
                        ]
                      }
                    }
                  }
                ]
              }
            }
          }
        }
      ]
    },
    "visualContainerObjects": {
      "background": [
        {
          "properties": {
            "show": {
              "expr": {
                "Literal": {
                  "Value": "false"
                }
              }
            }
          }
        }
      ]
    },
    "drillFilterOtherVisuals": true
  },
  "parentGroupName": "20634294900b89931ac3"
}