{
  "$schema": "https://developer.microsoft.com/json-schemas/fabric/item/report/definition/visualContainer/2.1.0/schema.json",
  "name": "7941c4a77bbfe3df0f52",
  "position": {
    "x": 0,
    "y": 0,
    "z": 0,
    "height": 61.313868613138688,
    "width": 300.56311908001368,
    "tabOrder": 7018
  },
  "visual": {
    "visualType": "slicer",
    "query": {
      "queryState": {
        "Values": {
          "projections": [
            {
              "field": {
                "Column": {
                  "Expression": {
                    "SourceRef": {
                      "Entity": "bi_view_comercial"
                    }
                  },
                  "Property": "representante_codigo_nome"
                }
              },
              "queryRef": "bi_view_comercial.representante_codigo_nome",
              "nativeQueryRef": "representante_codigo_nome",
              "active": true
            }
          ]
        }
      },
      "sortDefinition": {
        "isDefaultSort": true
      }
    },
    "objects": {
      "data": [
        {
          "properties": {
            "mode": {
              "expr": {
                "Literal": {
                  "Value": "'Dropdown'"
                }
              }
            }
          }
        }
      ],
      "selection": [
        {
          "properties": {
            "strictSingleSelect": {
              "expr": {
                "Literal": {
                  "Value": "false"
                }
              }
            },
            "selectAllCheckboxEnabled": {
              "expr": {
                "Literal": {
                  "Value": "true"
                }
              }
            },
            "singleSelect": {
              "expr": {
                "Literal": {
                  "Value": "false"
                }
              }
            }
          }
        }
      ],
      "general": [
        {
          "properties": {}
        }
      ],
      "items": [
        {
          "properties": {
            "fontColor": {
              "solid": {
                "color": {
                  "expr": {
                    "ThemeDataColor": {
                      "ColorId": 0,
                      "Percent": 0
                    }
                  }
                }
              }
            },
            "fontFamily": {
              "expr": {
                "Literal": {
                  "Value": "'wf_standard-font, helvetica, arial, sans-serif'"
                }
              }
            },
            "background": {
              "solid": {
                "color": {
                  "expr": {
                    "Literal": {
                      "Value": "'#09124F'"
                    }
                  }
                }
              }
            },
            "textSize": {
              "expr": {
                "Literal": {
                  "Value": "10D"
                }
              }
            }
          }
        }
      ],
      "header": [
        {
          "properties": {
            "fontColor": {
              "solid": {
                "color": {
                  "expr": {
                    "ThemeDataColor": {
                      "ColorId": 0,
                      "Percent": 0
                    }
                  }
                }
              }
            },
            "text": {
              "expr": {
                "Literal": {
                  "Value": "'Representante'"
                }
              }
            },
            "show": {
              "expr": {
                "Literal": {
                  "Value": "true"
                }
              }
            }
          }
        }
      ]
    },
    "visualContainerObjects": {
      "background": [
        {
          "properties": {
            "show": {
              "expr": {
                "Literal": {
                  "Value": "false"
                }
              }
            }
          }
        }
      ],
      "visualHeader": [
        {
          "properties": {
            "transparency": {
              "expr": {
                "Literal": {
                  "Value": "0D"
                }
              }
            }
          }
        }
      ]
    },
    "drillFilterOtherVisuals": true
  },
  "parentGroupName": "b7b3b5132ae2964cfc7a",
  "filterConfig": {
    "filters": [
      {
        "name": "2bab5a850e0be040db6e",
        "field": {
          "Measure": {
            "Expression": {
              "SourceRef": {
                "Entity": "Medidas"
              }
            },
            "Property": "Faturamento Liquido"
          }
        },
        "type": "Advanced",
        "filter": {
          "Version": 2,
          "From": [
            {
              "Name": "m",
              "Entity": "Medidas",
              "Type": 0
            }
          ],
          "Where": [
            {
              "Condition": {
                "Or": {
                  "Left": {
                    "Comparison": {
                      "ComparisonKind": 1,
                      "Left": {
                        "Measure": {
                          "Expression": {
                            "SourceRef": {
                              "Source": "m"
                            }
                          },
                          "Property": "Faturamento Liquido"
                        }
                      },
                      "Right": {
                        "Literal": {
                          "Value": "0L"
                        }
                      }
                    }
                  },
                  "Right": {
                    "Comparison": {
                      "ComparisonKind": 3,
                      "Left": {
                        "Measure": {
                          "Expression": {
                            "SourceRef": {
                              "Source": "m"
                            }
                          },
                          "Property": "Faturamento Liquido"
                        }
                      },
                      "Right": {
                        "Literal": {
                          "Value": "0L"
                        }
                      }
                    }
                  }
                }
              }
            }
          ]
        },
        "howCreated": "User"
      }
    ]
  }
}